whist_server/__init__.py
whist_server/__main__.py
whist_server/api/__init__.py
whist_server/api/api.py
whist_server/api/oauth2/__init__.py
whist_server/api/oauth2/github.py
whist_server/api/ranking/__init__.py
whist_server/api/ranking/leaderboard.py
whist_server/api/room/__init__.py
whist_server/api/room/action.py
whist_server/api/room/create.py
whist_server/api/room/game.py
whist_server/api/room/info.py
whist_server/api/room/join.py
whist_server/api/room/trick.py
whist_server/api/user/__init__.py
whist_server/api/user/auth.py
whist_server/api/user/create.py
whist_server/api/user/info.py
whist_server/api/util.py
whist_server/cli.py
whist_server/const.py
whist_server/database/__init__.py
whist_server/database/access_token.py
whist_server/database/connection.py
whist_server/database/error.py
whist_server/database/id_wrapper.py
whist_server/database/room.py
whist_server/database/token.py
whist_server/database/user.py
whist_server/database/warning.py
whist_server/services/__init__.py
whist_server/services/authentication.py
whist_server/services/channel_service.py
whist_server/services/error.py
whist_server/services/game_info_service.py
whist_server/services/github_service.py
whist_server/services/password.py
whist_server/services/ranking_service.py
whist_server/services/room_db_service.py
whist_server/services/splunk_service.py
whist_server/services/user_db_service.py
whist_server/web_socket/__init__.py
whist_server/web_socket/entry.py
whist_server/web_socket/events/__init__.py
whist_server/web_socket/events/event.py
whist_server/web_socket/side_channel.py
whist_server/web_socket/subscriber.py
whist_server-0.8.0.dist-info/LICENSE
whist_server-0.8.0.dist-info/METADATA
whist_server-0.8.0.dist-info/WHEEL
whist_server-0.8.0.dist-info/entry_points.txt
whist_server-0.8.0.dist-info/RECORD
