Metadata-Version: 2.1
Name: whist-server
Version: 0.8.0
Summary: Whist server implementation
Home-page: https://github.com/Whist-Team/Whist-Server
License: MIT
Keywords: game,server,whist
Author: Whist-Team
Requires-Python: >=3.9,<4.0
Classifier: License :: OSI Approved :: MIT License
Classifier: Operating System :: OS Independent
Classifier: Programming Language :: Python :: 3
Classifier: Programming Language :: Python :: 3.9
Classifier: Programming Language :: Python :: 3.10
Classifier: Programming Language :: Python :: 3.11
Classifier: Programming Language :: Python :: 3.12
Requires-Dist: PyJWT (>=2.8,<3.0)
Requires-Dist: bcrypt (>=4.1,<5.0)
Requires-Dist: fastapi (>=0.109,<0.110)
Requires-Dist: httpx (>=0.26,<0.27)
Requires-Dist: pydantic (>=2.6,<3.0)
Requires-Dist: pymongo (>=4.6,<5.0)
Requires-Dist: python-multipart (>=0.0.8,<0.0.9)
Requires-Dist: uvicorn (>=0.27,<0.28)
Requires-Dist: whist-core (>=0.9,<0.10)
Project-URL: Bug Tracker, https://github.com/Whist-Team/Whist-Server/issues
Project-URL: Repository, https://github.com/Whist-Team/Whist-Server
